jinja2_redis.py
setup.py
Jinja2_Redis.egg-info/PKG-INFO
Jinja2_Redis.egg-info/SOURCES.txt
Jinja2_Redis.egg-info/dependency_links.txt
Jinja2_Redis.egg-info/top_level.txt