Metadata-Version: 1.0
Name: Jinja2-Redis
Version: 0.1.2
Summary: Jinja2-Redis
Home-page: https://github.com/raicheff/jinja2-redis
Author: Boris Raicheff
Author-email: b@raicheff.com
License: UNKNOWN
Platform: UNKNOWN
